spatialprofilingtoolbox/__init__.py
spatialprofilingtoolbox/py.typed
spatialprofilingtoolbox/util.py
spatialprofilingtoolbox/apiserver/__init__.py
spatialprofilingtoolbox/apiserver/app/__init__.py
spatialprofilingtoolbox/apiserver/app/main.py
spatialprofilingtoolbox/apiserver/app/validation.py
spatialprofilingtoolbox/apiserver/app/versions.py
spatialprofilingtoolbox/apiserver/scripts/__init__.py
spatialprofilingtoolbox/apiserver/scripts/dump_schema.py
spatialprofilingtoolbox/db/__init__.py
spatialprofilingtoolbox/db/check_tables.py
spatialprofilingtoolbox/db/cohorts.py
spatialprofilingtoolbox/db/create_data_analysis_study.py
spatialprofilingtoolbox/db/credentials.py
spatialprofilingtoolbox/db/database_connection.py
spatialprofilingtoolbox/db/describe_features.py
spatialprofilingtoolbox/db/feature_matrix_extractor.py
spatialprofilingtoolbox/db/importance_score_transcriber.py
spatialprofilingtoolbox/db/modify_constraints.py
spatialprofilingtoolbox/db/ondemand_dropper.py
spatialprofilingtoolbox/db/ondemand_studies_index.py
spatialprofilingtoolbox/db/publish_promote.py
spatialprofilingtoolbox/db/querying.py
spatialprofilingtoolbox/db/schema_infuser.py
spatialprofilingtoolbox/db/shapefile_polygon.py
spatialprofilingtoolbox/db/simple_method_cache.py
spatialprofilingtoolbox/db/simple_query_patterns.py
spatialprofilingtoolbox/db/source_file_parser_interface.py
spatialprofilingtoolbox/db/squidpy_metrics.py
spatialprofilingtoolbox/db/stratification_puller.py
spatialprofilingtoolbox/db/study_dropper.py
spatialprofilingtoolbox/db/study_tokens.py
spatialprofilingtoolbox/db/verbose_sql_execution.py
spatialprofilingtoolbox/db/accessors/__init__.py
spatialprofilingtoolbox/db/accessors/cells.py
spatialprofilingtoolbox/db/accessors/feature_names.py
spatialprofilingtoolbox/db/accessors/graphs.py
spatialprofilingtoolbox/db/accessors/phenotypes.py
spatialprofilingtoolbox/db/accessors/study.py
spatialprofilingtoolbox/db/data_model/__init__.py
spatialprofilingtoolbox-1.0.11.dist-info/METADATA
spatialprofilingtoolbox-1.0.11.dist-info/WHEEL
spatialprofilingtoolbox-1.0.11.dist-info/entry_points.txt
spatialprofilingtoolbox-1.0.11.dist-info/top_level.txt
spatialprofilingtoolbox-1.0.11.dist-info/RECORD
